rest_easy/__init__.py
rest_easy/exceptions.py
rest_easy/fields.py
rest_easy/models.py
rest_easy/patterns.py
rest_easy/registers.py
rest_easy/runtests.py
rest_easy/scopes.py
rest_easy/serializers.py
rest_easy/views.py
django_rest_easy-1.0.4.dist-info/LICENSE
django_rest_easy-1.0.4.dist-info/METADATA
django_rest_easy-1.0.4.dist-info/WHEEL
django_rest_easy-1.0.4.dist-info/top_level.txt
django_rest_easy-1.0.4.dist-info/RECORD
