Metadata-Version: 2.1
Name: django-rest-easy
Version: 1.0.4
Summary: django-rest-easy is an extension to DRF providing QOL improvements to serializers and views.
Home-page: https://github.com/bujniewicz/django-rest-easy
Author: Krzysztof Bujniewicz
Author-email: racech@gmail.com
License: MIT
Keywords: django,DRF,rest framework,serializers,viewsets
Platform: UNKNOWN
Classifier: Development Status :: 5 - Production/Stable
Classifier: License :: OSI Approved :: MIT License
Classifier: Programming Language :: Python :: 2
Classifier: Programming Language :: Python :: 2.7
Classifier: Programming Language :: Python :: 3
Classifier: Programming Language :: Python :: 3.4
Classifier: Programming Language :: Python :: 3.5
Classifier: Programming Language :: Python :: 3.6
Classifier: Programming Language :: Python :: 3.7
Requires-Python: >=2.7, !=3.0.*, !=3.1.*, !=3.2.*, !=3.3.*, <4
Requires-Dist: django (>=1.8.0)
Requires-Dist: djangorestframework (>=3.0.0)
Requires-Dist: setuptools (>=36.0.1)
Requires-Dist: six
